anji_core/__init__.py
anji_core/backend.py
anji_core/flow.py
anji_core/internal.py
anji_core/messages.py
anji_core/migrations.py
anji_core/nodes.py
anji_core/prehooks.py
anji_core/report.py
anji_core/security.py
anji_core/statistic.py
anji_core/test.py
anji_core/types.py
anji_core/users.py
anji_core/utils.py
anji_core/backends/__init__.py
anji_core/backends/slack.plug
anji_core/backends/slack.py
anji_core/backends/telegram.plug
anji_core/backends/telegram.py
anji_core/backends/test.plug
anji_core/backends/test.py
anji_core/cartridges/__init__.py
anji_core/cartridges/core.py
anji_core/cartridges/decorators.py
anji_core/cli/__init__.py
anji_core/cli/pid_control.py
anji_core/cli/utils.py
anji_core/events/__init__.py
anji_core/events/base.py
anji_core/help/__init__.py
anji_core/help/faq.py
anji_core/help/help.py
anji_core/manager/__init__.py
anji_core/manager/base.py
anji_core/manager/secure.py
anji_core/render/__init__.py
anji_core/render/base.py
anji_core/render/slack.py
anji_core/render/telegram.py
anji_core/render/test.py
anji_core/services/__init__.py
anji_core/services/cartridge.py
anji_core/services/compose_service.py
anji_core/services/core.py
anji_core/services/docker_service.py
anji_core/services/systemd_service.py
anji_core/signals/__init__.py
anji_core/signals/base.py
anji_core/signals/cartridge.py
anji_core/signals/producer.py
anji_core/tasks/__init__.py
anji_core/tasks/base.py
anji_core/tasks/cron.py
anji_core/tasks/decorators.py
anji_core/tasks/regular.py
anji_core/tasks/utils.py
anji_core-0.8.11.dist-info/DESCRIPTION.rst
anji_core-0.8.11.dist-info/METADATA
anji_core-0.8.11.dist-info/RECORD
anji_core-0.8.11.dist-info/WHEEL
anji_core-0.8.11.dist-info/entry_points.txt
anji_core-0.8.11.dist-info/metadata.json
anji_core-0.8.11.dist-info/top_level.txt
tests/__init__.py
tests/base_config.py
tests/test_simple.py
